tacimeicalc/README.MD
tacimeicalc/__init__.py
tacimeicalc/requirements.txt
tacimeicalc/thirdparty.json
tacimeicalc-0.10.dist-info/LICENSE.rst
tacimeicalc-0.10.dist-info/METADATA
tacimeicalc-0.10.dist-info/WHEEL
tacimeicalc-0.10.dist-info/top_level.txt
tacimeicalc-0.10.dist-info/RECORD
