Metadata-Version: 2.1
Name: tacimeicalc
Version: 0.10
Summary: Generates phone-related data including IMSI, IMEI, ICCID, MAC address, and phone number
Home-page: https://github.com/hansalemaos/tacimeicalc
Author: Johannes Fischer
Author-email: aulasparticularesdealemaosp@gmail.com
License: MIT
Keywords: android
Classifier: Development Status :: 4 - Beta
Classifier: Programming Language :: Python :: 3 :: Only
Classifier: Programming Language :: Python :: 3.10
Classifier: Topic :: Software Development :: Libraries :: Python Modules
Classifier: Topic :: Utilities
License-File: LICENSE.rst
